serialmonitor/__init__.py
serialmonitor/__main__.py
serialmonitor/app.py
serialmonitor/run.py
serialmonitor/config/config.toml
serialmonitor/modules/__init__.py
serialmonitor/styles/main.tcss
serialmonitor/utils/__init__.py
serialmonitor/utils/colors.py
serialmonitor/widgets/__init__.py
serialmonitor/widgets/serial_tabs.py
python_serialmonitor-1.1.8.dist-info/METADATA
python_serialmonitor-1.1.8.dist-info/WHEEL
python_serialmonitor-1.1.8.dist-info/entry_points.txt
python_serialmonitor-1.1.8.dist-info/RECORD
