Metadata-Version: 2.4
Name: python-serialmonitor
Version: 1.1.8
Summary: Python Serial Monitor
Author-email: Vivatsathorn Thitasirivit <vivatsathorn@outlook.co.th>
Requires-Python: >=3.10
Requires-Dist: libgcs
Requires-Dist: pyserial
Requires-Dist: textual
